server/__init__.py
server/server.py
server/common/__init__.py
server/common/decos.py
server/common/errors.py
server/common/utils.py
server/common/variables.py
server/logs/__init__.py
server/logs/config_server_log.py
server/server_files/__init__.py
server/server_files/add_user.py
server/server_files/config_window.py
server/server_files/core.py
server/server_files/delete_user.py
server/server_files/main_window.py
server/server_files/server_db.py
server/server_files/stats_window.py
chargaka_messenger_server-0.1.1.dist-info/METADATA
chargaka_messenger_server-0.1.1.dist-info/WHEEL
chargaka_messenger_server-0.1.1.dist-info/top_level.txt
chargaka_messenger_server-0.1.1.dist-info/RECORD
