Metadata-Version: 2.1
Name: chargaka-messenger-server
Version: 0.1.1
Summary: chargaka_messenger_server
Author: Artem
Author-email: warload22@gmail.com
Requires-Dist: PyQt5
Requires-Dist: sqlalchemy
Requires-Dist: pycryptodome
Requires-Dist: pycryptodomex
